MANIFEST.in
README.rst
setup.py
bin/pystun
pystun.egg-info/PKG-INFO
pystun.egg-info/SOURCES.txt
pystun.egg-info/dependency_links.txt
pystun.egg-info/not-zip-safe
pystun.egg-info/top_level.txt
stun/__init__.py
stun/cli.py