Metadata-Version: 1.0
Name: pystun
Version: 0.0.4
Summary: A Python STUN client for getting NAT type and external IP (RFC 3489)
Home-page: http://github.com/jtriley/pystun
Author: Justin Riley (original author: gaohawk)
Author-email: justin.t.riley@gmail.com
License: MIT
Platform: UNKNOWN
Classifier: License :: OSI Approved :: MIT License
Classifier: Topic :: Internet
Classifier: Topic :: System :: Networking :: Firewalls
Classifier: Programming Language :: Python
